bqt/__init__.py
bqt/focus.py
bqt/manager.py
bqt/utils.py
bqt/blender_applications/__init__.py
bqt/blender_applications/blender_application.py
bqt/blender_applications/darwin_blender_application.py
bqt/blender_applications/win32_blender_application.py
bqt/ui/__init__.py
bqt/ui/question.svg
bqt/ui/quit_dialogue.py
bqt-2.1.0.dist-info/licenses/LICENSE
bqt_demo/__init__.py
bqt_demo/anim_bar.py
bqt_demo/demo.py
bqt_demo/hello_world.py
bqt_demo/pyside_widgets.py
bqt_demo/timer.py
bqt-2.1.0.dist-info/METADATA
bqt-2.1.0.dist-info/WHEEL
bqt-2.1.0.dist-info/top_level.txt
bqt-2.1.0.dist-info/RECORD
