Metadata-Version: 2.4
Name: bqt
Version: 2.1.0
Summary: Files to help bootstrap PySide6 with an event loop within Blender.
Author: tech-artists.org
License-Expression: MPL-2.0
Project-URL: Homepage, https://github.com/techartorg/bqt
Project-URL: Repository, https://github.com/techartorg/bqt
Project-URL: Issues, https://github.com/techartorg/bqt/issues
Project-URL: Documentation, https://github.com/techartorg/bqt/wiki
Keywords: Technical,Art,TechArt,TechArtOrg,Blender,Qt,PySide,tool,pipeline,gamedev,vfx,3d
Classifier: Development Status :: 5 - Production/Stable
Classifier: Intended Audience :: Developers
Classifier: Programming Language :: Python :: 3.11
Classifier: Programming Language :: Python :: 3.12
Classifier: Operating System :: OS Independent
Classifier: Topic :: Software Development :: Libraries
Classifier: Topic :: Multimedia :: Graphics :: 3D Modeling
Requires-Python: >=3.11
License-File: LICENSE
Requires-Dist: PySide6
Requires-Dist: blender-qt-stylesheet
Dynamic: license-file
